{
    "body": "[{\"id\":451,\"content\":\"easy\"},{\"id\":452,\"content\":\"bashful\"},{\"id\":453,\"content\":\"nimble\"},{\"id\":454,\"content\":\"fresh\"},{\"id\":455,\"content\":\"lovely\"},{\"id\":456,\"content\":\"racist\"},{\"id\":457,\"content\":\"mindless\"},{\"id\":458,\"content\":\"fluffy\"},{\"id\":459,\"content\":\"acid\"},{\"id\":460,\"content\":\"ruthless\"},{\"id\":461,\"content\":\"workable\"},{\"id\":462,\"content\":\"redundant\"},{\"id\":463,\"content\":\"concerned\"},{\"id\":464,\"content\":\"flagrant\"},{\"id\":465,\"content\":\"three\"},{\"id\":466,\"content\":\"jolly\"},{\"id\":467,\"content\":\"delightful\"},{\"id\":468,\"content\":\"necessary\"},{\"id\":469,\"content\":\"obscene\"},{\"id\":470,\"content\":\"ugly\"},{\"id\":471,\"content\":\"sticky\"},{\"id\":472,\"content\":\"threatening\"},{\"id\":473,\"content\":\"hideous\"},{\"id\":474,\"content\":\"disillusioned\"},{\"id\":475,\"content\":\"imported\"}]"
}